{
  "training_rows": 200,
  "accuracy_threshold": 0.7,
  "max_iterations": 20,
  "iterations": [
    {
      "iteration": 1,
      "accuracy": 0.735,
      "best_accuracy": 0.735,
      "timestamp": "2025-09-03 12:38:33",
      "above_threshold": true
    },
    {
      "iteration": 2,
      "accuracy": 0.68,
      "best_accuracy": 0.735,
      "timestamp": "2025-09-03 12:40:57",
      "above_threshold": false,
      "is_validation": true,
      "validation_gap": 0.05499999999999994
    },
    {
      "iteration": 2,
      "accuracy": 0.68,
      "best_accuracy": 0.735,
      "timestamp": "2025-09-03 12:41:09",
      "above_threshold": false,
      "is_validation": true,
      "validation_gap": 0.05499999999999994
    }
  ],
  "validation_accuracy": 0.68
}